cdr/__init__.py
cdr/backend.py
cdr/baselines.py
cdr/config.py
cdr/data.py
cdr/formula.py
cdr/io.py
cdr/kwargs.py
cdr/model.py
cdr/opt.py
cdr/plot.py
cdr/signif.py
cdr/sphinx.py
cdr/synth.py
cdr/util.py
cdr/bin/__init__.py
cdr/bin/compare_init.py
cdr/bin/convolve.py
cdr/bin/create_config.py
cdr/bin/help.py
cdr/bin/lmer.py
cdr/bin/lrt.py
cdr/bin/make_jobs.py
cdr/bin/metrics.py
cdr/bin/partition.py
cdr/bin/plot.py
cdr/bin/predict.py
cdr/bin/query.py
cdr/bin/signif_table.py
cdr/bin/stitch.py
cdr/bin/summarize.py
cdr/bin/synth.py
cdr/bin/test.py
cdr/bin/train.py
cdr/templates/__init__.py
cdr/templates/cdr_model_template.ini
cdr/templates/cdr_plot_template.ini
cdr/viz/__init__.py
cdr/viz/app.py
cdr/viz/assets/viz.css
cdr/viz/assets_tmp/base.css
cdr/viz/assets_tmp/general-app-page.css
cdrnn-0.8.5.dist-info/LICENSE.txt
cdrnn-0.8.5.dist-info/METADATA
cdrnn-0.8.5.dist-info/WHEEL
cdrnn-0.8.5.dist-info/top_level.txt
cdrnn-0.8.5.dist-info/RECORD
